Metadata-Version: 1.1
Name: pygal-maps-world
Version: 1.0.0
Summary: World maps for pygal
Home-page: http://pygal.org/
Author: Kozea
Author-email: florian.mounier@kozea.fr
License: GNU LGPL v3+
Keywords: svg,chart,graph,maps,world
Platform: Any
Classifier: Development Status :: 4 - Beta
Classifier: Environment :: Console
Classifier: Intended Audience :: End Users/Desktop
Classifier: License :: OSI Approved :: GNU Lesser General Public License v3 or later (LGPLv3+)
Classifier: Operating System :: OS Independent
Classifier: Programming Language :: Python :: 2
Classifier: Programming Language :: Python :: 3
Classifier: Topic :: Multimedia :: Graphics :: Presentation
Provides: pygal_maps_world
